{"latitude":46.2546,"longitude":20.1486,"timezone":"Europe/Budapest","offset":1,"hourly":{"summary":"Mostly cloudy throughout the day.","icon":"partly-cloudy-day","data":[{"time":1231110000,"summary":"Overcast","icon":"cloudy","precipType":"snow","temperature":22,"apparentTemperature":11.97,"dewPoint":17.08,"humidity":0.81,"windSpeed":9,"windBearing":210,"visibility":4.4,"cloudCover":1,"pressure":1019.9},{"time":1231113600,"summary":"Partly Cloudy","icon":"partly-cloudy-night","precipType":"snow","temperature":17.59,"apparentTemperature":17.59,"dewPoint":15.61,"humidity":0.92,"windSpeed":1.83,"windBearing":39,"visibility":2.51,"cloudCover":0.42,"pressure":1021.18},{"time":1231117200,"summary":"Overcast","icon":"cloudy","precipType":"snow","temperature":22,"apparentTemperature":11.97,"dewPoint":17.92,"humidity":0.84,"windSpeed":9,"windBearing":180,"visibility":3.8,"cloudCover":1,"pressure":1019.3},{"time":1231120800,"summary":"Overcast","icon":"cloudy","precipType":"snow","temperature":21,"apparentTemperature":10.74,"dewPoint":16.94,"humidity":0.84,"windSpeed":9,"windBearing":190,"visibility":3.8,"cloudCover":1,"pressure":1019.2},{"time":1231124400,"summary":"Mostly Cloudy","icon":"partly-cloudy-night","precipType":"snow","temperature":20.16,"apparentTemperature":10.81,"dewPoint":16.21,"humidity":0.84,"windSpeed":7.5,"windBearing":180,"visibility":3.94,"cloudCover":0.7,"pressure":1019.12},{"time":1231128000,"summary":"Mostly Cloudy","icon":"partly-cloudy-night","precipType":"snow","temperature":19,"apparentTemperature":9.83,"dewPoint":16.04,"humidity":0.88,"windSpeed":7,"windBearing":170,"visibility":3.8,"cloudCover":0.75,"pressure":1018.9},{"time":1231131600,"summary":"Mostly Cloudy","icon":"partly-cloudy-night","precipType":"snow","temperature":19,"apparentTemperature":9.83,"dewPoint":16.04,"humidity":0.88,"windSpeed":7,"windBearing":160,"visibility":3.8,"cloudCover":0.75,"pressure":1018.9},{"time":1231135200,"summary":"Mostly Cloudy","icon":"partly-cloudy-night","precipType":"snow","temperature":18.94,"apparentTemperature":9.8,"dewPoint":14.16,"humidity":0.81,"windSpeed":6.94,"windBearing":177,"visibility":3.35,"cloudCover":0.89,"pressure":1019.11},{"time":1231138800,"summary":"Mostly Cloudy","icon":"partly-cloudy-day","precipType":"snow","temperature":19,"apparentTemperature":8.28,"dewPoint":16.04,"humidity":0.88,"windSpeed":9,"windBearing":180,"visibility":3.1,"cloudCover":0.75,"pressure":1019.2},{"time":1231142400,"summary":"Mostly Cloudy","icon":"partly-cloudy-day","precipType":"snow","temperature":21,"apparentTemperature":10.74,"dewPoint":16.1,"humidity":0.81,"windSpeed":9,"windBearing":180,"visibility":3.1,"cloudCover":0.75,"pressure":1019.7},{"time":1231146000,"summary":"Mostly Cloudy","icon":"partly-cloudy-day","precipType":"snow","temperature":22.78,"apparentTemperature":13.51,"dewPoint":18.08,"humidity":0.82,"windSpeed":8.16,"windBearing":160,"visibility":3.01,"cloudCover":0.71,"pressure":1020.32},{"time":1231149600,"summary":"Overcast","icon":"cloudy","precipType":"snow","temperature":23,"apparentTemperature":14.65,"dewPoint":18.06,"humidity":0.81,"windSpeed":7,"windBearing":170,"visibility":3.1,"cloudCover":1,"pressure":1020.2},{"time":1231153200,"summary":"Overcast","icon":"cloudy","precipType":"snow","temperature":25,"apparentTemperature":17.06,"dewPoint":17.9,"humidity":0.74,"windSpeed":7,"windBearing":160,"visibility":3.1,"cloudCover":1,"pressure":1019.7},{"time":1231156800,"summary":"Overcast","icon":"cloudy","precipType":"snow","temperature":24.81,"apparentTemperature":16.2,"dewPoint":19.06,"humidity":0.78,"windSpeed":7.85,"windBearing":145,"visibility":3.01,"cloudCover":0.98,"pressure":1019.33},{"time":1231160400,"summary":"Overcast","icon":"cloudy","precipType":"snow","temperature":25,"apparentTemperature":18.85,"dewPoint":19.13,"humidity":0.78,"windSpeed":5,"windBearing":130,"visibility":2.8,"cloudCover":1,"pressure":1018.9},{"time":1231164000,"summary":"Overcast","icon":"cloudy","precipType":"snow","temperature":23,"apparentTemperature":23,"dewPoint":18.9,"humidity":0.84,"windSpeed":2,"windBearing":150,"visibility":2.8,"cloudCover":1,"pressure":1019.2},{"time":1231167600,"summary":"Overcast","icon":"cloudy","precipType":"snow","temperature":23.03,"apparentTemperature":18.52,"dewPoint":18.88,"humidity":0.84,"windSpeed":3.42,"windBearing":120,"visibility":2.38,"cloudCover":0.98,"pressure":1019.49},{"time":1231171200,"summary":"Partly Cloudy","icon":"partly-cloudy-night","precipType":"snow","temperature":21,"apparentTemperature":21,"dewPoint":18.02,"humidity":0.88,"windSpeed":2,"windBearing":90,"visibility":2.5,"cloudCover":0.31,"pressure":1019.2},{"time":1231174800,"summary":"Mostly Cloudy","icon":"partly-cloudy-night","precipType":"snow","temperature":21,"apparentTemperature":21,"dewPoint":18.02,"humidity":0.88,"windSpeed":3,"windBearing":80,"visibility":2.5,"cloudCover":0.75,"pressure":1019.6},{"time":1231178400,"summary":"Mostly Cloudy","icon":"partly-cloudy-night","precipType":"snow","temperature":20.97,"apparentTemperature":20.97,"dewPoint":17.99,"humidity":0.88,"windSpeed":2.52,"windBearing":54,"visibility":2.5,"cloudCover":0.72,"pressure":1020.01},{"time":1231182000,"summary":"Partly Cloudy","icon":"partly-cloudy-night","precipType":"snow","temperature":21,"apparentTemperature":21,"dewPoint":18.02,"humidity":0.88,"windSpeed":2,"windBearing":50,"visibility":2.5,"cloudCover":0.31,"pressure":1020.3},{"time":1231185600,"summary":"Partly Cloudy","icon":"partly-cloudy-night","precipType":"snow","temperature":20,"apparentTemperature":14.22,"dewPoint":17.03,"humidity":0.88,"windSpeed":4,"windBearing":70,"visibility":2.5,"cloudCover":0.31,"pressure":1020.6},{"time":1231189200,"summary":"Partly Cloudy","icon":"partly-cloudy-night","precipType":"snow","temperature":18.16,"apparentTemperature":18.16,"dewPoint":15.37,"humidity":0.89,"windSpeed":2.73,"windBearing":25,"visibility":2.17,"cloudCover":0.31,"pressure":1021.11},{"time":1231192800,"summary":"Partly Cloudy","icon":"partly-cloudy-night","precipType":"snow","temperature":17,"apparentTemperature":7.42,"dewPoint":15.09,"humidity":0.92,"windSpeed":7,"windBearing":20,"visibility":2.2,"cloudCover":0.31,"pressure":1021.6}]},"daily":{"data":[{"time":1231110000,"summary":"Foggy overnight.","icon":"fog","sunriseTime":1231136595,"sunsetTime":1231168121,"moonPhase":0.29,"precipType":"snow","temperatureMin":17,"temperatureMinTime":1231192800,"temperatureMax":25,"temperatureMaxTime":1231160400,"apparentTemperatureMin":7.42,"apparentTemperatureMinTime":1231192800,"apparentTemperatureMax":18.85,"apparentTemperatureMaxTime":1231160400,"dewPoint":17.15,"humidity":0.85,"windSpeed":4.03,"windBearing":160,"visibility":3.03,"cloudCover":0.74,"pressure":1019.75}]}}