{"latitude":46.2546,"longitude":20.1486,"timezone":"Europe/Budapest","offset":2,"hourly":{"summary":"Partly cloudy starting overnight.","icon":"partly-cloudy-day","data":[{"time":1309384800,"summary":"Mostly Cloudy","icon":"partly-cloudy-night","precipType":"rain","temperature":66.71,"apparentTemperature":66.71,"dewPoint":63.33,"humidity":0.89,"windSpeed":4.67,"windBearing":313,"visibility":7.62,"cloudCover":0.72,"pressure":1009.4},{"time":1309388400,"summary":"Clear","icon":"clear-night","precipType":"rain","temperature":66,"apparentTemperature":66,"dewPoint":62.98,"humidity":0.9,"windSpeed":4,"windBearing":300,"visibility":6.2},{"time":1309392000,"summary":"Mostly Cloudy","icon":"partly-cloudy-night","precipType":"rain","temperature":62.21,"apparentTemperature":62.21,"dewPoint":59.62,"humidity":0.91,"windSpeed":10.08,"windBearing":300,"visibility":8.8,"cloudCover":0.75,"pressure":1010.16},{"time":1309395600,"summary":"Mostly Cloudy","icon":"partly-cloudy-night","precipType":"rain","temperature":62.92,"apparentTemperature":62.92,"dewPoint":62.04,"humidity":0.97,"windSpeed":2.09,"windBearing":290,"visibility":9.83,"cloudCover":0.75,"pressure":1008.74},{"time":1309399200,"summary":"Mostly Cloudy","icon":"partly-cloudy-night","precipType":"rain","temperature":62.95,"apparentTemperature":62.95,"dewPoint":62.07,"humidity":0.97,"windSpeed":3.76,"windBearing":274,"visibility":9.83,"cloudCover":0.75,"pressure":1008.62},{"time":1309402800,"summary":"Mostly Cloudy","icon":"partly-cloudy-day","precipType":"rain","temperature":63.09,"apparentTemperature":63.09,"dewPoint":62.14,"humidity":0.97,"windSpeed":2.25,"windBearing":301,"visibility":8.68,"cloudCover":0.75,"pressure":1008.62},{"time":1309406400,"summary":"Partly Cloudy","icon":"partly-cloudy-day","precipType":"rain","temperature":62.92,"apparentTemperature":62.92,"dewPoint":60.95,"humidity":0.93,"windSpeed":3.03,"windBearing":355,"visibility":6.15,"cloudCover":0.3,"pressure":1008.32},{"time":1309410000,"summary":"Mostly Cloudy","icon":"partly-cloudy-day","precipType":"rain","temperature":64.04,"apparentTemperature":64.04,"dewPoint":64,"humidity":1,"windSpeed":2.9,"windBearing":301,"visibility":6.91,"cloudCover":0.72,"pressure":1007.96},{"time":1309413600,"summary":"Partly Cloudy","icon":"partly-cloudy-day","precipType":"rain","temperature":67.89,"apparentTemperature":67.89,"dewPoint":63.35,"humidity":0.85,"windSpeed":5.19,"windBearing":354,"visibility":6.88,"cloudCover":0.39,"pressure":1008.34},{"time":1309417200,"summary":"Mostly Cloudy","icon":"partly-cloudy-day","precipType":"rain","temperature":71.89,"apparentTemperature":71.89,"dewPoint":61.01,"humidity":0.69,"windSpeed":1.98,"windBearing":345,"visibility":7,"cloudCover":0.75,"pressure":1008.11},{"time":1309420800,"summary":"Mostly Cloudy","icon":"partly-cloudy-day","precipType":"rain","temperature":76.51,"apparentTemperature":76.51,"dewPoint":62.96,"humidity":0.63,"windSpeed":0.21,"windBearing":310,"visibility":7,"cloudCover":0.75,"pressure":1008.11},{"time":1309424400,"summary":"Partly Cloudy","icon":"partly-cloudy-day","precipType":"rain","temperature":75.95,"apparentTemperature":75.95,"dewPoint":59.89,"humidity":0.58,"windSpeed":1.41,"windBearing":312,"visibility":7.11,"cloudCover":0.4,"pressure":1007.9},{"time":1309428000,"summary":"Partly Cloudy","icon":"partly-cloudy-day","precipType":"rain","temperature":74.66,"apparentTemperature":74.66,"dewPoint":61.35,"humidity":0.63,"windSpeed":6.59,"windBearing":262,"visibility":7,"cloudCover":0.33,"pressure":1007.84},{"time":1309431600,"summary":"Partly Cloudy","icon":"partly-cloudy-day","precipType":"rain","temperature":66.77,"apparentTemperature":66.77,"dewPoint":63.24,"humidity":0.88,"windSpeed":2.68,"windBearing":4,"visibility":7,"cloudCover":0.33,"pressure":1008.08},{"time":1309435200,"summary":"Partly Cloudy","icon":"partly-cloudy-day","precipType":"rain","temperature":70.74,"apparentTemperature":70.74,"dewPoint":64.09,"humidity":0.8,"windSpeed":4.58,"windBearing":326,"visibility":6.88,"cloudCover":0.43,"pressure":1008.28},{"time":1309438800,"summary":"Humid and Partly Cloudy","icon":"partly-cloudy-day","precipType":"rain","temperature":72.24,"apparentTemperature":72.24,"dewPoint":65.78,"humidity":0.8,"windSpeed":1.57,"windBearing":17,"visibility":6.77,"cloudCover":0.33,"pressure":1007.47},{"time":1309442400,"summary":"Partly Cloudy","icon":"partly-cloudy-day","precipType":"rain","temperature":76.15,"apparentTemperature":76.15,"dewPoint":65.95,"humidity":0.71,"windSpeed":5.82,"windBearing":317,"visibility":6.86,"cloudCover":0.34,"pressure":1006.95},{"time":1309446000,"summary":"Humid and Partly Cloudy","icon":"partly-cloudy-day","precipType":"rain","temperature":70.57,"apparentTemperature":70.57,"dewPoint":67.14,"humidity":0.89,"windSpeed":5.21,"windBearing":269,"visibility":4.92,"cloudCover":0.39,"pressure":1006.66},{"time":1309449600,"summary":"Mostly Cloudy","icon":"partly-cloudy-day","precipType":"rain","temperature":64.08,"apparentTemperature":64.08,"dewPoint":63.09,"humidity":0.97,"windSpeed":8.81,"windBearing":263,"visibility":5.09,"cloudCover":0.75,"pressure":1007.12},{"time":1309453200,"summary":"Partly Cloudy","icon":"partly-cloudy-day","precipType":"rain","temperature":64.05,"apparentTemperature":64.05,"dewPoint":63.85,"humidity":0.99,"windSpeed":8.87,"windBearing":320,"visibility":6.96,"cloudCover":0.33,"pressure":1008.09},{"time":1309456800,"summary":"Partly Cloudy","icon":"partly-cloudy-day","precipType":"rain","temperature":63.88,"apparentTemperature":63.88,"dewPoint":62.94,"humidity":0.97,"windSpeed":8.5,"windBearing":326,"visibility":6.85,"cloudCover":0.39,"pressure":1008.65},{"time":1309460400,"summary":"Mostly Cloudy","icon":"partly-cloudy-night","precipType":"rain","temperature":63.04,"apparentTemperature":63.04,"dewPoint":62.97,"humidity":1,"windSpeed":7.98,"windBearing":301,"visibility":6.2,"cloudCover":0.75,"pressure":1009.05},{"time":1309464000,"summary":"Partly Cloudy","icon":"partly-cloudy-night","precipType":"rain","temperature":63.96,"apparentTemperature":63.96,"dewPoint":61.85,"humidity":0.93,"windSpeed":10.64,"windBearing":300,"visibility":9.26,"cloudCover":0.33,"pressure":1009.46},{"time":1309467600,"summary":"Partly Cloudy","icon":"partly-cloudy-night","precipType":"rain","temperature":63.85,"apparentTemperature":63.85,"dewPoint":61.82,"humidity":0.93,"windSpeed":10.21,"windBearing":301,"visibility":8.8,"cloudCover":0.37,"pressure":1009.63}]},"daily":{"data":[{"time":1309384800,"summary":"Partly cloudy throughout the day.","icon":"partly-cloudy-day","sunriseTime":1309402313,"sunsetTime":1309458984,"moonPhase":0.96,"precipType":"rain","temperatureMin":62.21,"temperatureMinTime":1309392000,"temperatureMax":76.51,"temperatureMaxTime":1309420800,"apparentTemperatureMin":62.21,"apparentTemperatureMinTime":1309392000,"apparentTemperatureMax":76.51,"apparentTemperatureMaxTime":1309420800,"dewPoint":62.85,"humidity":0.87,"windSpeed":4.59,"windBearing":305,"visibility":7.27,"cloudCover":0.53,"pressure":1008.33}]}}