{"latitude":46.2546,"longitude":20.1486,"timezone":"Europe/Budapest","offset":2,"hourly":{"summary":"Mostly cloudy throughout the day.","icon":"partly-cloudy-day","data":[{"time":1178920800,"summary":"Partly Cloudy","icon":"partly-cloudy-night","precipType":"rain","temperature":63.38,"apparentTemperature":63.38,"dewPoint":52.84,"humidity":0.69,"windSpeed":6.87,"windBearing":211,"visibility":9.83,"cloudCover":0.31,"pressure":1009.34},{"time":1178924400,"summary":"Partly Cloudy","icon":"partly-cloudy-night","precipType":"rain","temperature":61.55,"apparentTemperature":61.55,"dewPoint":50.97,"humidity":0.68,"windSpeed":7.12,"windBearing":250,"visibility":9.83,"cloudCover":0.33,"pressure":1009.53},{"time":1178928000,"summary":"Partly Cloudy","icon":"partly-cloudy-night","precipType":"rain","temperature":53.92,"apparentTemperature":53.92,"dewPoint":49.02,"humidity":0.83,"windSpeed":7.32,"windBearing":248,"visibility":9.24,"cloudCover":0.25,"pressure":1015.51},{"time":1178931600,"summary":"Partly Cloudy","icon":"partly-cloudy-night","precipType":"rain","temperature":59.37,"apparentTemperature":59.37,"dewPoint":47.07,"humidity":0.64,"windSpeed":6.74,"windBearing":264,"visibility":9.83,"cloudCover":0.33,"pressure":1009.58},{"time":1178935200,"summary":"Mostly Cloudy","icon":"partly-cloudy-night","precipType":"rain","temperature":59.33,"apparentTemperature":59.33,"dewPoint":48.16,"humidity":0.66,"windSpeed":8.75,"windBearing":273,"visibility":9.83,"cloudCover":0.75,"pressure":1010.1},{"time":1178938800,"summary":"Mostly Cloudy","icon":"partly-cloudy-night","precipType":"rain","temperature":57.15,"apparentTemperature":57.15,"dewPoint":48.47,"humidity":0.73,"windSpeed":6.99,"windBearing":305,"visibility":9.29,"cloudCover":0.68,"pressure":1010.88},{"time":1178942400,"summary":"Mostly Cloudy","icon":"partly-cloudy-day","precipType":"rain","temperature":59.29,"apparentTemperature":59.29,"dewPoint":50.04,"humidity":0.71,"windSpeed":7.78,"windBearing":319,"visibility":6.96,"cloudCover":0.75,"pressure":1011.78},{"time":1178946000,"summary":"Mostly Cloudy","icon":"partly-cloudy-day","precipType":"rain","temperature":60.21,"apparentTemperature":60.21,"dewPoint":50.15,"humidity":0.69,"windSpeed":6.92,"windBearing":318,"visibility":9.83,"cloudCover":0.75,"pressure":1012.39},{"time":1178949600,"summary":"Mostly Cloudy","icon":"partly-cloudy-day","precipType":"rain","temperature":63.23,"apparentTemperature":63.23,"dewPoint":51.8,"humidity":0.66,"windSpeed":7.98,"windBearing":311,"visibility":7.11,"cloudCover":0.72,"pressure":1013.32},{"time":1178953200,"summary":"Mostly Cloudy","icon":"partly-cloudy-day","precipType":"rain","temperature":65.78,"apparentTemperature":65.78,"dewPoint":48.11,"humidity":0.53,"windSpeed":10.55,"windBearing":330,"visibility":6.24,"cloudCover":0.75,"pressure":1014.19},{"time":1178956800,"summary":"Mostly Cloudy","icon":"partly-cloudy-day","precipType":"rain","temperature":67.58,"apparentTemperature":67.58,"dewPoint":46.14,"humidity":0.46,"windSpeed":8.75,"windBearing":329,"visibility":6.24,"cloudCover":0.75,"pressure":1014.4},{"time":1178960400,"summary":"Mostly Cloudy","icon":"partly-cloudy-day","precipType":"rain","temperature":66.25,"apparentTemperature":66.25,"dewPoint":45.4,"humidity":0.47,"windSpeed":9.72,"windBearing":341,"visibility":6.46,"cloudCover":0.72,"pressure":1015.25},{"time":1178964000,"summary":"Mostly Cloudy","icon":"partly-cloudy-day","precipType":"rain","temperature":67.66,"apparentTemperature":67.66,"dewPoint":45.7,"humidity":0.45,"windSpeed":6.69,"windBearing":8,"visibility":6.24,"cloudCover":0.75,"pressure":1015.48},{"time":1178967600,"summary":"Partly Cloudy","icon":"partly-cloudy-day","precipType":"rain","temperature":67.62,"apparentTemperature":67.62,"dewPoint":48.74,"humidity":0.51,"windSpeed":4.47,"windBearing":5,"visibility":7,"cloudCover":0.33,"pressure":1015.32},{"time":1178971200,"summary":"Mostly Cloudy","icon":"partly-cloudy-day","precipType":"rain","temperature":66.51,"apparentTemperature":66.51,"dewPoint":47.57,"humidity":0.51,"windSpeed":5.62,"windBearing":357,"visibility":6.46,"cloudCover":0.76,"pressure":1015.54},{"time":1178974800,"summary":"Partly Cloudy","icon":"partly-cloudy-day","precipType":"rain","temperature":68.21,"apparentTemperature":68.21,"dewPoint":48.45,"humidity":0.49,"windSpeed":1.81,"windBearing":327,"visibility":6.96,"cloudCover":0.33,"pressure":1015.24},{"time":1178978400,"summary":"Mostly Cloudy","icon":"partly-cloudy-day","precipType":"rain","temperature":70.09,"apparentTemperature":70.09,"dewPoint":46.28,"humidity":0.43,"windSpeed":3.2,"windBearing":227,"visibility":6.24,"cloudCover":0.75,"pressure":1014.65},{"time":1178982000,"summary":"Mostly Cloudy","icon":"partly-cloudy-day","precipType":"rain","temperature":71.79,"apparentTemperature":71.79,"dewPoint":45.98,"humidity":0.4,"windSpeed":2.22,"windBearing":200,"visibility":6.43,"cloudCover":0.75,"pressure":1014.28},{"time":1178985600,"summary":"Mostly Cloudy","icon":"partly-cloudy-day","precipType":"rain","temperature":71.92,"apparentTemperature":71.92,"dewPoint":48.46,"humidity":0.43,"windSpeed":1.17,"windBearing":226,"visibility":6.2,"cloudCover":0.75,"pressure":1013.98},{"time":1178989200,"summary":"Mostly Cloudy","icon":"partly-cloudy-day","precipType":"rain","temperature":70,"apparentTemperature":70,"dewPoint":46.36,"humidity":0.43,"windSpeed":3.29,"windBearing":235,"visibility":6.2,"cloudCover":0.75,"pressure":1014.07},{"time":1178992800,"summary":"Mostly Cloudy","icon":"partly-cloudy-night","precipType":"rain","temperature":63.92,"apparentTemperature":63.92,"dewPoint":51.56,"humidity":0.64,"windSpeed":2.46,"windBearing":178,"visibility":6.46,"cloudCover":0.71,"pressure":1014.68},{"time":1178996400,"summary":"Mostly Cloudy","icon":"partly-cloudy-night","precipType":"rain","temperature":57.16,"apparentTemperature":57.16,"dewPoint":50.11,"humidity":0.77,"windSpeed":1.84,"windBearing":150,"visibility":6.2,"cloudCover":0.75,"pressure":1015.43},{"time":1179000000,"summary":"Partly Cloudy","icon":"partly-cloudy-night","precipType":"rain","temperature":57.08,"apparentTemperature":57.08,"dewPoint":51.01,"humidity":0.8,"windSpeed":1.89,"windBearing":200,"visibility":9.83,"cloudCover":0.31,"pressure":1015.97},{"time":1179003600,"summary":"Partly Cloudy","icon":"partly-cloudy-night","precipType":"rain","temperature":56.47,"apparentTemperature":56.47,"dewPoint":52,"humidity":0.85,"windSpeed":1.48,"windBearing":169,"visibility":9.51,"cloudCover":0.27,"pressure":1016.13}]},"daily":{"data":[{"time":1178920800,"summary":"Mostly cloudy throughout the day.","icon":"partly-cloudy-day","sunriseTime":1178939519,"sunsetTime":1178992933,"moonPhase":0.84,"precipType":"rain","temperatureMin":53.92,"temperatureMinTime":1178928000,"temperatureMax":71.92,"temperatureMaxTime":1178985600,"apparentTemperatureMin":53.92,"apparentTemperatureMinTime":1178928000,"apparentTemperatureMax":71.92,"apparentTemperatureMaxTime":1178985600,"dewPoint":48.77,"humidity":0.6,"windSpeed":3.45,"windBearing":298,"visibility":7.68,"cloudCover":0.6,"pressure":1013.63}]}}