{"latitude":46.2546,"longitude":20.1486,"timezone":"Europe/Budapest","offset":1,"hourly":{"summary":"Mostly cloudy throughout the day.","icon":"partly-cloudy-day","data":[{"time":1478559600,"summary":"Partly Cloudy","icon":"partly-cloudy-night","precipType":"rain","temperature":40.57,"temperatureError":7.08,"apparentTemperature":36.84,"dewPoint":38.21,"dewPointError":2.28,"humidity":0.91,"humidityError":0.08,"windSpeed":5.4,"windSpeedError":3.94,"windBearing":170,"windBearingError":36.08,"visibility":7.46,"visibilityError":4.03,"cloudCover":0.55,"cloudCoverError":0.4,"pressure":1019.58,"pressureError":8.37},{"time":1478563200,"summary":"Partly Cloudy","icon":"partly-cloudy-night","precipType":"rain","temperature":39.92,"temperatureError":6.99,"apparentTemperature":36.03,"dewPoint":37.91,"dewPointError":2.36,"humidity":0.92,"humidityError":0.09,"windSpeed":5.47,"windSpeedError":3.93,"windBearing":172,"windBearingError":35.68,"visibility":5.93,"visibilityError":3.92,"cloudCover":0.55,"cloudCoverError":0.41,"pressure":1019.5,"pressureError":8.66},{"time":1478566800,"summary":"Partly Cloudy","icon":"partly-cloudy-night","precipType":"rain","temperature":39.31,"temperatureError":6.97,"apparentTemperature":35.28,"dewPoint":37.46,"dewPointError":2.09,"humidity":0.93,"humidityError":0.08,"windSpeed":5.51,"windSpeedError":3.95,"windBearing":170,"windBearingError":35.66,"visibility":6.34,"visibilityError":3.83,"cloudCover":0.55,"cloudCoverError":0.41,"pressure":1019.39,"pressureError":8.41},{"time":1478570400,"summary":"Partly Cloudy","icon":"partly-cloudy-night","precipType":"rain","temperature":38.81,"temperatureError":7.02,"apparentTemperature":34.67,"dewPoint":36.95,"dewPointError":2.04,"humidity":0.93,"humidityError":0.07,"windSpeed":5.54,"windSpeedError":4.01,"windBearing":166,"windBearingError":35.89,"visibility":5.48,"visibilityError":3.76,"cloudCover":0.55,"cloudCoverError":0.41,"pressure":1019.31,"pressureError":8.37},{"time":1478574000,"summary":"Partly Cloudy","icon":"partly-cloudy-night","precipType":"rain","temperature":38.56,"temperatureError":7.14,"apparentTemperature":34.33,"dewPoint":36.49,"dewPointError":2.33,"humidity":0.92,"humidityError":0.08,"windSpeed":5.6,"windSpeedError":4.09,"windBearing":159,"windBearingError":36.16,"visibility":4.15,"visibilityError":3.71,"cloudCover":0.56,"cloudCoverError":0.4,"pressure":1019.3,"pressureError":8.66},{"time":1478577600,"summary":"Partly Cloudy","icon":"partly-cloudy-night","precipType":"rain","temperature":38.69,"temperatureError":7.31,"apparentTemperature":34.39,"dewPoint":36.23,"dewPointError":2.28,"humidity":0.91,"humidityError":0.08,"windSpeed":5.72,"windSpeedError":4.2,"windBearing":152,"windBearingError":36.26,"visibility":4.84,"visibilityError":3.7,"cloudCover":0.56,"cloudCoverError":0.4,"pressure":1019.36,"pressureError":8.41},{"time":1478581200,"summary":"Partly Cloudy","icon":"partly-cloudy-night","precipType":"rain","temperature":39.29,"temperatureError":7.54,"apparentTemperature":34.95,"dewPoint":36.29,"dewPointError":2.45,"humidity":0.89,"humidityError":0.09,"windSpeed":5.96,"windSpeedError":4.32,"windBearing":149,"windBearingError":35.95,"visibility":3.65,"visibilityError":3.72,"cloudCover":0.57,"cloudCoverError":0.39,"pressure":1019.48,"pressureError":8.38},{"time":1478584800,"summary":"Partly Cloudy","icon":"partly-cloudy-day","precipType":"rain","temperature":40.42,"temperatureError":7.8,"apparentTemperature":36.06,"dewPoint":36.74,"dewPointError":2.97,"humidity":0.87,"humidityError":0.1,"windSpeed":6.32,"windSpeedError":4.45,"windBearing":149,"windBearingError":35.15,"visibility":3.91,"visibilityError":3.76,"cloudCover":0.59,"cloudCoverError":0.38,"pressure":1019.64,"pressureError":8.67},{"time":1478588400,"summary":"Mostly Cloudy","icon":"partly-cloudy-day","precipType":"rain","temperature":42.02,"temperatureError":8.08,"apparentTemperature":37.68,"dewPoint":37.55,"dewPointError":3.1,"humidity":0.84,"humidityError":0.1,"windSpeed":6.8,"windSpeedError":4.58,"windBearing":153,"windBearingError":33.96,"visibility":4.96,"visibilityError":3.84,"cloudCover":0.6,"cloudCoverError":0.37,"pressure":1019.78,"pressureError":8.42},{"time":1478592000,"summary":"Mostly Cloudy","icon":"partly-cloudy-day","precipType":"rain","temperature":43.92,"temperatureError":8.35,"apparentTemperature":39.69,"dewPoint":38.62,"dewPointError":3.43,"humidity":0.81,"humidityError":0.11,"windSpeed":7.34,"windSpeedError":4.7,"windBearing":157,"windBearingError":32.63,"visibility":4.35,"visibilityError":3.93,"cloudCover":0.61,"cloudCoverError":0.36,"pressure":1019.86,"pressureError":8.38},{"time":1478595600,"summary":"Mostly Cloudy","icon":"partly-cloudy-day","precipType":"rain","temperature":45.92,"temperatureError":8.6,"apparentTemperature":41.86,"dewPoint":39.78,"dewPointError":4.09,"humidity":0.79,"humidityError":0.12,"windSpeed":7.86,"windSpeedError":4.8,"windBearing":163,"windBearingError":31.41,"visibility":5.95,"visibilityError":4.04,"cloudCover":0.62,"cloudCoverError":0.35,"pressure":1019.84,"pressureError":8.67},{"time":1478599200,"summary":"Mostly Cloudy","icon":"partly-cloudy-day","precipType":"rain","temperature":47.75,"temperatureError":8.81,"apparentTemperature":43.91,"dewPoint":40.83,"dewPointError":4.24,"humidity":0.77,"humidityError":0.13,"windSpeed":8.27,"windSpeedError":4.88,"windBearing":169,"windBearingError":30.52,"visibility":6.34,"visibilityError":4.16,"cloudCover":0.63,"cloudCoverError":0.34,"pressure":1019.71,"pressureError":8.42},{"time":1478602800,"summary":"Mostly Cloudy","icon":"partly-cloudy-day","precipType":"rain","temperature":49.17,"temperatureError":8.96,"apparentTemperature":45.56,"dewPoint":41.61,"dewPointError":4.51,"humidity":0.75,"humidityError":0.13,"windSpeed":8.49,"windSpeedError":4.92,"windBearing":173,"windBearingError":30.1,"visibility":6.07,"visibilityError":4.28,"cloudCover":0.63,"cloudCoverError":0.33,"pressure":1019.48,"pressureError":8.39},{"time":1478606400,"summary":"Mostly Cloudy","icon":"partly-cloudy-day","precipType":"rain","temperature":50.01,"temperatureError":9.05,"apparentTemperature":50.01,"dewPoint":42,"dewPointError":5.05,"humidity":0.74,"humidityError":0.14,"windSpeed":8.46,"windSpeedError":4.93,"windBearing":176,"windBearingError":30.24,"visibility":7.45,"visibilityError":4.38,"cloudCover":0.64,"cloudCoverError":0.33,"pressure":1019.19,"pressureError":8.67},{"time":1478610000,"summary":"Mostly Cloudy","icon":"partly-cloudy-day","precipType":"rain","temperature":50.19,"temperatureError":9.08,"apparentTemperature":50.19,"dewPoint":41.97,"dewPointError":4.92,"humidity":0.73,"humidityError":0.14,"windSpeed":8.18,"windSpeedError":4.91,"windBearing":176,"windBearingError":30.99,"visibility":6.47,"visibilityError":4.48,"cloudCover":0.64,"cloudCoverError":0.32,"pressure":1018.9,"pressureError":8.43},{"time":1478613600,"summary":"Mostly Cloudy","icon":"partly-cloudy-day","precipType":"rain","temperature":49.73,"temperatureError":9.03,"apparentTemperature":46.57,"dewPoint":41.56,"dewPointError":4.86,"humidity":0.73,"humidityError":0.14,"windSpeed":7.67,"windSpeedError":4.86,"windBearing":172,"windBearingError":32.36,"visibility":6.49,"visibilityError":4.55,"cloudCover":0.64,"cloudCoverError":0.33,"pressure":1018.68,"pressureError":8.39},{"time":1478617200,"summary":"Mostly Cloudy","icon":"partly-cloudy-day","precipType":"rain","temperature":48.75,"temperatureError":8.91,"apparentTemperature":45.67,"dewPoint":40.9,"dewPointError":5.02,"humidity":0.74,"humidityError":0.14,"windSpeed":7.03,"windSpeedError":4.78,"windBearing":165,"windBearingError":34.19,"visibility":6.94,"visibilityError":4.59,"cloudCover":0.63,"cloudCoverError":0.33,"pressure":1018.55,"pressureError":8.68},{"time":1478620800,"summary":"Mostly Cloudy","icon":"partly-cloudy-night","precipType":"rain","temperature":47.46,"temperatureError":8.73,"apparentTemperature":44.42,"dewPoint":40.13,"dewPointError":4.53,"humidity":0.76,"humidityError":0.13,"windSpeed":6.41,"windSpeedError":4.67,"windBearing":158,"windBearingError":36.06,"visibility":5.56,"visibilityError":4.6,"cloudCover":0.62,"cloudCoverError":0.34,"pressure":1018.56,"pressureError":8.43},{"time":1478624400,"summary":"Mostly Cloudy","icon":"partly-cloudy-night","precipType":"rain","temperature":46.04,"temperatureError":8.51,"apparentTemperature":42.99,"dewPoint":39.39,"dewPointError":4.17,"humidity":0.77,"humidityError":0.13,"windSpeed":5.93,"windSpeedError":4.55,"windBearing":153,"windBearingError":37.48,"visibility":6.44,"visibilityError":4.58,"cloudCover":0.61,"cloudCoverError":0.34,"pressure":1018.68,"pressureError":8.39},{"time":1478628000,"summary":"Mostly Cloudy","icon":"partly-cloudy-night","precipType":"rain","temperature":44.67,"temperatureError":8.25,"apparentTemperature":41.62,"dewPoint":38.81,"dewPointError":4.08,"humidity":0.8,"humidityError":0.13,"windSpeed":5.5,"windSpeedError":4.42,"windBearing":151,"windBearingError":38.78,"visibility":6.32,"visibilityError":4.53,"cloudCover":0.6,"cloudCoverError":0.36,"pressure":1018.88,"pressureError":8.68},{"time":1478631600,"summary":"Partly Cloudy","icon":"partly-cloudy-night","precipType":"rain","temperature":43.46,"temperatureError":7.98,"apparentTemperature":40.35,"dewPoint":38.44,"dewPointError":3.48,"humidity":0.82,"humidityError":0.11,"windSpeed":5.27,"windSpeedError":4.29,"windBearing":153,"windBearingError":39.14,"visibility":5.83,"visibilityError":4.46,"cloudCover":0.59,"cloudCoverError":0.37,"pressure":1019.12,"pressureError":8.43},{"time":1478635200,"summary":"Partly Cloudy","icon":"partly-cloudy-night","precipType":"rain","temperature":42.47,"temperatureError":7.71,"apparentTemperature":39.22,"dewPoint":38.26,"dewPointError":3.08,"humidity":0.85,"humidityError":0.1,"windSpeed":5.22,"windSpeedError":4.17,"windBearing":157,"windBearingError":38.64,"visibility":7.28,"visibilityError":4.36,"cloudCover":0.58,"cloudCoverError":0.38,"pressure":1019.34,"pressureError":8.4},{"time":1478638800,"summary":"Partly Cloudy","icon":"partly-cloudy-night","precipType":"rain","temperature":41.65,"temperatureError":7.46,"apparentTemperature":38.22,"dewPoint":38.19,"dewPointError":3,"humidity":0.87,"humidityError":0.1,"windSpeed":5.27,"windSpeedError":4.07,"windBearing":161,"windBearingError":37.69,"visibility":6.55,"visibilityError":4.25,"cloudCover":0.57,"cloudCoverError":0.39,"pressure":1019.5,"pressureError":8.68},{"time":1478642400,"summary":"Partly Cloudy","icon":"partly-cloudy-night","precipType":"rain","temperature":40.95,"temperatureError":7.25,"apparentTemperature":37.32,"dewPoint":38.13,"dewPointError":2.52,"humidity":0.9,"humidityError":0.09,"windSpeed":5.36,"windSpeedError":4,"windBearing":166,"windBearingError":36.68,"visibility":6.84,"visibilityError":4.14,"cloudCover":0.56,"cloudCoverError":0.4,"pressure":1019.56,"pressureError":8.44}]},"daily":{"data":[{"time":1478559600,"summary":"Mostly cloudy throughout the day.","icon":"partly-cloudy-day","sunriseTime":1478583131,"sunsetTime":1478618209,"moonPhase":0.28,"precipType":"rain","temperatureMin":38.56,"temperatureMinError":7.14,"temperatureMinTime":1478574000,"temperatureMax":50.19,"temperatureMaxError":9.08,"temperatureMaxTime":1478610000,"apparentTemperatureMin":34.33,"apparentTemperatureMinTime":1478574000,"apparentTemperatureMax":50.19,"apparentTemperatureMaxTime":1478610000,"dewPoint":38.85,"dewPointError":3.6,"humidity":0.83,"humidityError":0.11,"windSpeed":6.36,"windSpeedError":4.45,"windBearing":163,"windBearingError":34.95,"visibility":5.9,"visibilityError":4.16,"cloudCover":0.59,"cloudCoverError":0.37,"pressure":1019.3,"pressureError":8.49}]}}